{
  "Item": [
    {
      "ItemID": 10000,
      "Name": "단검",
      "Description": "짧은 단검",
      "UnlockLev": 1,
      "MaxHP": 0,
      "MaxHPMul": 0,
      "MaxMP": 0,
      "MaxMPMul": 0,
      "MaxAtk": 16,
      "MaxAtkMul": 1.1,
      "MaxDef": 0,
      "MaxDefMul": 0,
      "Status": 0
    },
    {
      "ItemID": 10001,
      "Name": "장갑",
      "Description": "얇은 장갑",
      "UnlockLev": 1,
      "MaxHP": 10,
      "MaxHPMul": 0,
      "MaxMP": 0,
      "MaxMPMul": 0,
      "MaxAtk": 5,
      "MaxAtkMul": 1.1,
      "MaxDef": 0,
      "MaxDefMul": 0,
      "Status": 0
    }
  ]
}